LICENSE
MANIFEST.in
install_script.py
requirements.txt
setup.py
bin/luwu.py
luwu/__init__.py
luwu/run.py
luwu.egg-info/PKG-INFO
luwu.egg-info/SOURCES.txt
luwu.egg-info/dependency_links.txt
luwu.egg-info/top_level.txt
luwu/backend/__init__.py
luwu/backend/app.py
luwu/backend/config.py
luwu/backend/model.py
luwu/backend/v1.py
luwu/backend/views.py
luwu/core/__init__.py
luwu/core/models/__init__.py
luwu/core/models/image.py
luwu/core/models/text.py
luwu/core/models/classifier/__init__.py
luwu/core/models/classifier/autokeras/__init__.py
luwu/core/models/classifier/autokeras/image_classifier.py
luwu/core/models/classifier/kerastuner/__init__.py
luwu/core/models/classifier/kerastuner/image_classifier.py
luwu/core/models/classifier/nni/__init__.py
luwu/core/models/classifier/preset/__init__.py
luwu/core/models/classifier/preset/pre_trained.py
luwu/core/models/classifier/preset/templates/LuwuPreTrainedImageClassifier.py
luwu/core/models/classifier/preset/templates/LuwuPreTrainedImageClassifier.txt
luwu/core/models/complex/__init__.py
luwu/core/models/complex/od/__init__.py
luwu/core/models/complex/od/models.py
luwu/core/models/complex/od/templates/pipeline/CenterNet_HourGlass104_512x512.jinja
luwu/core/models/complex/od/templates/pipeline/CenterNet_Resnet101_V1_FPN_512x512.jinja
luwu/core/models/complex/od/templates/pipeline/EfficientDet_D0_512x512.jinja
luwu/core/models/complex/od/templates/pipeline/SSD_ResNet50_V1_FPN_640x640_(RetinaNet50).jinja
luwu/core/models/complex/od/templates/project/eval.jinja
luwu/core/models/complex/od/templates/project/eval.py
luwu/core/models/complex/od/utils/__init__.py
luwu/core/models/complex/od/utils/generate_tfrecord.py
luwu/core/models/complex/od/utils/label_map_util.py
luwu/core/models/kaggle/__init__.py
luwu/core/models/kaggle/kaggle.py
luwu/core/models/kaggle/templates/notebook.json
luwu/core/models/regressor/__init__.py
luwu/core/models/text_classifier/__init__.py
luwu/core/models/text_classifier/transformers.py
luwu/core/models/text_classifier/templates/TransformerTextClassifier.jinja
