Metadata-Version: 1.2
Name: luwu
Version: 0.32
Summary: LuWu——陆吾，一个简单的无代码深度学习平台。
Home-page: https://github.com/AaronJny/luwu
Author: AaronJny
Author-email: aaronjny7@gmail.com
License: UNKNOWN
Platform: UNKNOWN
Requires-Python: >=3.6.5
